fastxlsx-0.2.0.dist-info/METADATA
fastxlsx-0.2.0.dist-info/WHEEL
fastxlsx-0.2.0.dist-info/licenses/LICENSE
fastxlsx/__init__.py
fastxlsx/__init__.pyi
fastxlsx/py.typed
fastxlsx/fastxlsx.cpython-310-i386-linux-gnu.so
fastxlsx-0.2.0.dist-info/RECORD
