Metadata-Version: 2.4
Name: fastxlsx
Version: 0.2.0
Classifier: Programming Language :: Rust
Classifier: Programming Language :: Python :: Implementation :: CPython
Classifier: Programming Language :: Python :: Implementation :: PyPy
Requires-Dist: numpy
Requires-Dist: pytest ; extra == 'bench'
Requires-Dist: pytest-benchmark ; extra == 'bench'
Requires-Dist: openpyxl ; extra == 'bench'
Requires-Dist: xlsxwriter ; extra == 'bench'
Requires-Dist: pyexcelerate ; extra == 'bench'
Requires-Dist: python-calamine ; extra == 'bench'
Requires-Dist: pylightxl ; extra == 'bench'
Requires-Dist: pytest ; extra == 'dev'
Requires-Dist: ruff >=0.8.4 ; extra == 'dev'
Provides-Extra: bench
Provides-Extra: dev
License-File: LICENSE
Summary: A high-performance Excel XLSX reader/writer for Python built with Rust.
Keywords: excel,xlsx
Author-email: shuangluoxss <shuangluoxss@qq.com>
Maintainer-email: shuangluoxss <shuangluoxss@qq.com>
License: MIT
Requires-Python: >=3.8, <3.13
Project-URL: Homepage, https://github.com/shuangluoxss/fastxlsx
Project-URL: Repository, https://github.com/shuangluoxss/fastxlsx
Project-URL: Issues, https://github.com/shuangluoxss/fastxlsx/issues
Project-URL: Documentation, https://fastxlsx.readthedocs.io/
